[
	{
		"name": "Cloth Trousers",
		"type": "Legs",
		"rarity": 1,
		"sellPrice": [25],
		"dimensInvent": {
			"width": 2, "height": 3
		},
		"attributeMods": [
			{"attribute": "Dexterity", "value": 5},
			{"attribute": "Precision", "value": 3},
			{"attribute": "Constitution", "value": 2},
			{"attribute": "Defense", "value": 1},
			{"attribute": "Velocity", "value": 5},
			{"attribute": "DamageReductionPhysical", "value": 1},
			{"attribute": "DamageReductionMagical", "value": 2}
		],
		"abilities": []
	}, {
		"name": "Cloth Shirt",
		"type": "Chest",
		"rarity": 1,
		"sellPrice": [25],
		"dimensInvent": {
			"width": 2, "height": 3
		},
		"attributeMods": [
			{"attribute": "Dexterity", "value": 4},
			{"attribute": "Precision", "value": 4},
			{"attribute": "Constitution", "value": 1},
			{"attribute": "Defense", "value": 2},
			{"attribute": "DamageReductionPhysical", "value": 1},
			{"attribute": "DamageReductionMagical", "value": 2}
		],
		"abilities": []
	}, {
		"name": "Cloth Sleeve",
		"type": "Arms",
		"rarity": 1,
		"sellPrice": [8],
		"dimensInvent": {
			"width": 1, "height": 2
		},
		"attributeMods": [
			{"attribute": "Dexterity", "value": 3},
			{"attribute": "Precision", "value": 5},
			{"attribute": "Constitution", "value": 1},
			{"attribute": "Defense", "value": 1},
			{"attribute": "ProbabilityAvoidPhysical", "value": 10},
			{"attribute": "DamageReductionPhysical", "value": 1},
			{"attribute": "DamageReductionMagical", "value": 2}
		],
		"abilities": []
	}, {
		"name": "Cloth Shoes",
		"type": "Feet",
		"rarity": 1,
		"sellPrice": [20],
		"dimensInvent": {
			"width": 2, "height": 2
		},
		"attributeMods": [
			{"attribute": "Dexterity", "value": 5},
			{"attribute": "Constitution", "value": 1},
			{"attribute": "Defense", "value": 2},
			{"attribute": "Velocity", "value": 5},
			{"attribute": "ProbabilityAvoidPhysical", "value": 10},
			{"attribute": "ProbabilityAvoidMagical", "value": 10},
			{"attribute": "DamageReductionPhysical", "value": 1},
			{"attribute": "DamageReductionMagical", "value": 2}
		],
		"abilities": []
	}, {
		"name": "Cloth Hat",
		"type": "Head",
		"rarity": 1,
		"sellPrice": [12],
		"dimensInvent": {
			"width": 2, "height": 2
		},
		"attributeMods": [
			{"attribute": "Defense", "value": 3},
			{"attribute": "Constitution", "value": 2},
			{"attribute": "Precision", "value": 2},
			{"attribute": "CriticalProbabilityAvoid", "value": 5},
			{"attribute": "DamageReductionPhysical", "value": 1},
			{"attribute": "DamageReductionMagical", "value": 1}
		],
		"abilities": []
	}, {
		"name": "Cloth Hood",
		"type": "Head",
		"rarity": 1,
		"sellPrice": [18],
		"dimensInvent": {
			"width": 2, "height": 2
		},
		"attributeMods": [
			{"attribute": "Defense", "value": 3},
			{"attribute": "Constitution", "value": 3},
			{"attribute": "CriticalMultiplierReduction", "value": 5},
			{"attribute": "DamageReductionPhysical", "value": 1},
			{"attribute": "DamageReductionMagical", "value": 2}
		],
		"abilities": []
	}, {
		"name": "Cloth Gloves",
		"type": "Hands",
		"rarity": 1,
		"sellPrice": [15],
		"dimensInvent": {
			"width": 2, "height": 2
		},
		"attributeMods": [
			{"attribute": "Defense", "value": 2},
			{"attribute": "Constitution", "value": 1},
			{"attribute": "Precision", "value": 4},
			{"attribute": "Dexterity", "value": 3},
			{"attribute": "DamageReductionPhysical", "value": 1},
			{"attribute": "DamageReductionMagical", "value": 1}
		],
		"abilities": []
	}, {
		"name": "Cloth Cape",
		"type": "Shoulder",
		"rarity": 1,
		"sellPrice": [21],
		"dimensInvent": {
			"width": 2, "height": 4
		},
		"attributeMods": [
			{"attribute": "Defense", "value": 5},
			{"attribute": "Constitution", "value": 3},
			{"attribute": "Dexterity", "value": -2},
			{"attribute": "Precision", "value": -1},
			{"attribute": "Faith", "value": 1},
			{"attribute": "Velocity", "value": -2},
			{"attribute": "DamageReductionPhysical", "value": 1},
			{"attribute": "DamageReductionMagical", "value": 3}
		],
		"abilities": []
	}, {
		"name": "Wool Cap",
		"type": "Head",
		"rarity": 1,
		"sellPrice": [18],
		"dimensInvent": {
			"width": 2, "height": 2
		},
		"attributeMods": [
			{"attribute": "Constitution", "value": 4},
			{"attribute": "Health", "value": 1},
			{"attribute": "Defense", "value": 5},
			{"attribute": "Dexterity", "value": -2},
			{"attribute": "Precision", "value": -2},
			{"attribute": "DamageReductionPhysical", "value": 1},
			{"attribute": "DamageReductionMagical", "value": 2}
		],
		"abilities": []
	}, {
		"name": "Wool Gloves",
		"type": "Hands",
		"rarity": 1,
		"sellPrice": [25],
		"dimensInvent": {
			"width": 2, "height": 2
		},
		"attributeMods": [
			{"attribute": "Strength", "value": 2},
			{"attribute": "Constitution", "value": 2},
			{"attribute": "Health", "value": 1},
			{"attribute": "Defense", "value": 4},
			{"attribute": "Precision", "value": -1},
			{"attribute": "Dexterity", "value": -2},
			{"attribute": "DamageReductionPhysical", "value": 2},
			{"attribute": "DamageReductionMagical", "value": 2}
		],
		"abilities": []
	}, {
		"name": "Wool Sleeve",
		"type": "Arms",
		"rarity": 1,
		"sellPrice": [8],
		"dimensInvent": {
			"width": 1, "height": 2
		},
		"attributeMods": [
			{"attribute": "Strength", "value": 3},
			{"attribute": "Defense", "value": 5},
			{"attribute": "Constitution", "value": 3},
			{"attribute": "Health", "value": 2},
			{"attribute": "Dexterity", "value": -2},
			{"attribute": "Precision", "value": -3},
			{"attribute": "DamageReductionPhysical", "value": 2},
			{"attribute": "DamageReductionMagical", "value": 3}
		],
		"abilities": []
	}, {
		"name": "Wool Trousers",
		"type": "Legs",
		"rarity": 1,
		"sellPrice": [27],
		"dimensInvent": {
			"width": 2, "height": 3
		},
		"attributeMods": [
			{"attribute": "LifeMax", "value": 10},
			{"attribute": "Defense", "value": 7},
			{"attribute": "Constitution", "value": 3},
			{"attribute": "Health", "value": 2},
			{"attribute": "Dexterity", "value": -4},
			{"attribute": "Precision", "value": -2},
			{"attribute": "Velocity", "value": -3},
			{"attribute": "DamageReductionPhysical", "value": 3},
			{"attribute": "DamageReductionMagical", "value": 3}
		],
		"abilities": []
	}, {
		"name": "Wool Pullover",
		"type": "Chest",
		"description": "A warm shirt of raw wool, a uncomfortable for soft skins but smooths hurts.",
		"rarity": 1,
		"sellPrice": [28],
		"dimensInvent": {
			"width": 2, "height": 3
		},
		"attributeMods": [
			{"attribute": "LifeMax", "value": 15},
			{"attribute": "Defense", "value": 7},
			{"attribute": "Constitution", "value": 4},
			{"attribute": "Health", "value": 2},
			{"attribute": "Dexterity", "value": -2},
			{"attribute": "Precision", "value": -4},
			{"attribute": "RegenLife", "value": -1},
			{"attribute": "DamageReductionPhysical", "value": 4},
			{"attribute": "DamageReductionMagical", "value": 2}
		],
		"abilities": []
	}, {
		"name": "Wool Shoes",
		"type": "Feet",
		"rarity": 1,
		"sellPrice": [27],
		"dimensInvent": {
			"width": 2, "height": 2
		},
		"attributeMods": [
			{"attribute": "Defense", "value": 3},
			{"attribute": "Constitution", "value": 2},
			{"attribute": "Health", "value": 1},
			{"attribute": "Dexterity", "value": 2},
			{"attribute": "Precision", "value": -2},
			{"attribute": "Velocity", "value": 5},
			{"attribute": "DamageReductionPhysical", "value": 1},
			{"attribute": "DamageReductionMagical", "value": 1}
		],
		"abilities": []
	}, {
		"name": "Wool Mantle",
		"type": "Shoulder",
		"rarity": 1,
		"sellPrice": [25],
		"dimensInvent": {
			"width": 2, "height": 4
		},
		"attributeMods": [
			{"attribute": "Defense", "value": 8},
			{"attribute": "Constitution", "value": 5},
			{"attribute": "Health", "value": 2},
			{"attribute": "Dexterity", "value": -4},
			{"attribute": "Precision", "value": -2},
			{"attribute": "Velocity", "value": -4},
			{"attribute": "DamageReductionPhysical", "value": 2},
			{"attribute": "DamageReductionMagical", "value": 4}
		],
		"abilities": []
	}, {
		"name": "Leather Trousers",
		"type": "Legs",
		"rarity": 2,
		"sellPrice": [40],
		"dimensInvent": {
			"width": 2, "height": 3
		},
		"attributeMods": [
			{"attribute": "LifeMax", "value": 23},
			{"attribute": "Defense", "value": 6},
			{"attribute": "Constitution", "value": 7},
			{"attribute": "Health", "value": -2},
			{"attribute": "Dexterity", "value": -3},
			{"attribute": "Velocity", "value": -3},
			{"attribute": "DamageReductionPhysical", "value": 3},
			{"attribute": "DamageReductionMagical", "value": 1}
		],
		"abilities": []
	}, {
		"name": "Leather Jacket",
		"type": "Chest",
		"rarity": 1,
		"sellPrice": [40],
		"dimensInvent": {
			"width": 2, "height": 3
		},
		"attributeMods": [
			{"attribute": "LifeMax", "value": 18},
			{"attribute": "Defense", "value": 7},
			{"attribute": "Constitution", "value": 8},
			{"attribute": "Health", "value": -3},
			{"attribute": "Precision", "value": 2},
			{"attribute": "Dexterity", "value": -5},
			{"attribute": "DamageReductionPhysical", "value": 4}
		],
		"abilities": []
	}, {
		"name": "Leather Shoes",
		"type": "Feet",
		"rarity": 2,
		"sellPrice": [34],
		"dimensInvent": {
			"width": 2, "height": 2
		},
		"attributeMods": [
			{"attribute": "Defense", "value": 5},
			{"attribute": "Constitution", "value": 7},
			{"attribute": "Dexterity", "value": 5},
			{"attribute": "Health", "value": -1},
			{"attribute": "Velocity", "value": 10},
			{"attribute": "ManaMax", "value": -10},
			{"attribute": "DamageReductionPhysical", "value": 3}
		],
		"abilities": []
	}, {
		"name": "Leather Boots",
		"type": "Feet",
		"rarity": 2,
		"sellPrice": [37],
		"dimensInvent": {
			"width": 2, "height": 2
		},
		"attributeMods": [
			{"attribute": "Defense", "value": 6},
			{"attribute": "Constitution", "value": 8},
			{"attribute": "Health", "value": -2},
			{"attribute": "Dexterity", "value": 3},
			{"attribute": "Velocity", "value": 7},
			{"attribute": "ManaMax", "value": -5},
			{"attribute": "DamageReductionPhysical", "value": 3}
		],
		"abilities": []
	}, {
		"name": "Leather Cap",
		"type": "Head",
		"rarity": 2,
		"sellPrice": [28],
		"dimensInvent": {
			"width": 2, "height": 2
		},
		"attributeMods": [
			{"attribute": "LifeMax", "value": 11},
			{"attribute": "Defense", "value": 4},
			{"attribute": "Constitution", "value": 5},
			{"attribute": "Health", "value": -2},
			{"attribute": "DamageReductionPhysical", "value": 3},
			{"attribute": "DamageReductionMagical", "value": 1},
			{"attribute": "CriticalMultiplierReduction", "value": 7}
		],
		"abilities": []
	}, {
		"name": "Leather Gloves",
		"type": "Hands",
		"rarity": 2,
		"sellPrice": [22],
		"dimensInvent": {
			"width": 2, "height": 2
		},
		"attributeMods": [
			{"attribute": "Defense", "value": 3},
			{"attribute": "Constitution", "value": 2},
			{"attribute": "Health", "value": -2},
			{"attribute": "Precision", "value": 3},
			{"attribute": "Dexterity", "value": 4},
			{"attribute": "DamageReductionPhysical", "value": 2},
			{"attribute": "ProbabilityHitPhysical", "value": 3},
			{"attribute": "ProbabilityHitMagical", "value": 3}
		],
		"abilities": []
	}, {
		"name": "Leather Sleeve",
		"type": "Arms",
		"rarity": 2,
		"sellPrice": [13],
		"dimensInvent": {
			"width": 1, "height": 2
		},
		"attributeMods": [
			{"attribute": "Strength", "value": 3},
			{"attribute": "Defense", "value": 4},
			{"attribute": "Constitution", "value": 6},
			{"attribute": "Health", "value": -2},
			{"attribute": "Precision", "value": 4},
			{"attribute": "Dexterity", "value": -5},
			{"attribute": "DamageReductionPhysical", "value": 2},
			{"attribute": "CriticalMultiplierReduction", "value": 5},
			{"attribute": "DamageReductionMagical", "value": 2}
		],
		"abilities": []
	}, {
		"name": "Leather Cloak",
		"type": "Shoulder",
		"rarity": 2,
		"sellPrice": [35],
		"dimensInvent": {
			"width": 2, "height": 4
		},
		"attributeMods": [
			{"attribute": "Defense", "value": 10},
			{"attribute": "Constitution", "value": 10},
			{"attribute": "Dexterity", "value": -6},
			{"attribute": "Precision", "value": -4},
			{"attribute": "Faith", "value": -3},
			{"attribute": "Velocity", "value": -10},
			{"attribute": "DamageReductionPhysical", "value": 4},
			{"attribute": "DamageReductionMagical", "value": 5}
		],
		"abilities": []
	}, {
		"name": "Chainmail Trousers",
		"type": "Legs",
		"rarity": 2,
		"sellPrice": [37],
		"dimensInvent": {
			"width": 2, "height": 2
		},
		"attributeMods": [ TODOOOOOOOOOOOOOOOOOOOOOOOOOOOOOOOOOOOOOOOOOOOOOOOOOOOOOOOOOOOOOOOOOOOOOOOOOOOOOOOOOOOOOOOOOOOOOOOOOOOOOOOOOOOOOOOOOOOOOOOOOOOOOOO
			{"attribute": "LifeMax", "value": -20},
			{"attribute": "Defense", "value": 6},
			{"attribute": "Constitution", "value": 5},
			{"attribute": "Health", "value": -2},
			{"attribute": "DamageReductionPhysical", "value": 5},
			{"attribute": "DamageReductionMagical", "value": -2},
			{"attribute": "CriticalMultiplierReduction", "value": 10}
		],
		"abilities": []
	}, {
		"name": "Chainmail Brigandine",
		"type": "Head",
		"rarity": 2,
		"sellPrice": [37],
		"dimensInvent": {
			"width": 2, "height": 2
		},
		"attributeMods": [
			{"attribute": "LifeMax", "value": -20},
			{"attribute": "Defense", "value": 6},
			{"attribute": "Constitution", "value": 5},
			{"attribute": "Health", "value": -2},
			{"attribute": "DamageReductionPhysical", "value": 5},
			{"attribute": "DamageReductionMagical", "value": -2},
			{"attribute": "CriticalMultiplierReduction", "value": 10}
		],
		"abilities": []
	}, {
		"name": "Chainmail Coif",
		"type": "Head",
		"rarity": 2,
		"sellPrice": [37],
		"dimensInvent": {
			"width": 2, "height": 2
		},
		"attributeMods": [
			{"attribute": "LifeMax", "value": -20},
			{"attribute": "Defense", "value": 6},
			{"attribute": "Constitution", "value": 5},
			{"attribute": "Health", "value": -2},
			{"attribute": "DamageReductionPhysical", "value": 5},
			{"attribute": "DamageReductionMagical", "value": -2},
			{"attribute": "CriticalMultiplierReduction", "value": 10}
		],
		"abilities": []
	}, {
		"name": "Feather Wings",
		"type": "Shoulder",
		"rarity": 1,
		"sellPrice": [7],
		"dimensInvent": {
			"width": 4, "height": 2
		},
		"attributeMods": [
			{"attribute": "Dexterity", "value": 7},
			{"attribute": "Precision", "value": -3},
			{"attribute": "Wisdom", "value": -2},
			{"attribute": "Velocity", "value": 5},
			{"attribute": "ProbabilityAvoidPhysical", "value": 15},
			{"attribute": "ProbabilityAvoidMagical", "value": 15},
			{"attribute": "CriticalProbabilityAvoid", "value": 15}
		],
		"abilities": []
	}, {
		"name": "Angel Wings",
		"type": "Shoulder",
		"rarity": 4,
		"sellPrice": [255],
		"dimensInvent": {
			"width": 4, "height": 3
		},
		"attributeMods": [
			{"attribute": "Dexterity", "value": 12},
			{"attribute": "Health", "value": 3},
			{"attribute": "Faith", "value": 7},
			{"attribute": "DamageBonusPhysical", "value": -5},
			{"attribute": "DamageBonusMagical", "value": -5},
			{"attribute": "CriticalProbability", "value": -30},
			{"attribute": "CriticalMultiplier", "value": -15},
			{"attribute": "ProbabilityAvoidPhysical", "value": 40},
			{"attribute": "ProbabilityAvoidMagical", "value": 40},
			{"attribute": "CriticalProbabilityAvoid", "value": 40}
		],
		"abilities": []
	}, {
		"name": "Demon Wings",
		"type": "Shoulder",
		"rarity": 4,
		"sellPrice": [255],
		"dimensInvent": {
			"width": 4, "height": 3
		},
		"attributeMods": [
			{"attribute": "Dexterity", "value": 8},
			{"attribute": "Precision", "value": 4},
			{"attribute": "Strength", "value": 7},
			{"attribute": "Faith", "value": -10},
			{"attribute": "Wisdom", "value": -5},
			{"attribute": "ManaMax", "value": 20},
			{"attribute": "DamageBonusPhysical", "value": 2},
			{"attribute": "DamageBonusMagical", "value": 2},
			{"attribute": "LifeLeechPercentage", "value": 5},
			{"attribute": "ManaLeechPercentage", "value": 5}
		],
		"abilities": []
	}, {
		"name": "Wood plated Trousers", // TODO OOO WOOOOOOOOOD
		"type": "Legs",
		"rarity": 2,
		"sellPrice": [10],
		"dimensInvent": {
			"width": 2, "height": 3
		},
		"attributeMods": [ // TANTA destrezza e velocita', un po' di precisione e costituzione, tanta difesa magica, - health, + faith - intelligenza
			{"attribute": "LifeMax", "value": 23},
			{"attribute": "Defense", "value": 6},
			{"attribute": "Constitution", "value": 7},
			{"attribute": "Health", "value": -2},
			{"attribute": "Dexterity", "value": -3},
			{"attribute": "Velocity", "value": -3},
			{"attribute": "DamageReductionPhysical", "value": 3},
			{"attribute": "DamageReductionMagical", "value": 1}
		],
		"abilities": []
	}, {
		"name": "Leather Jacket",
		"type": "Chest",
		"rarity": 1,
		"sellPrice": [40],
		"dimensInvent": {
			"width": 2, "height": 3
		},
		"attributeMods": [
			{"attribute": "LifeMax", "value": 18},
			{"attribute": "Defense", "value": 7},
			{"attribute": "Constitution", "value": 8},
			{"attribute": "Health", "value": -3},
			{"attribute": "Precision", "value": 2},
			{"attribute": "Dexterity", "value": -5},
			{"attribute": "DamageReductionPhysical", "value": 4}
		],
		"abilities": []
	}, {
		"name": "Leather Shoes",
		"type": "Feet",
		"rarity": 2,
		"sellPrice": [34],
		"dimensInvent": {
			"width": 2, "height": 2
		},
		"attributeMods": [
			{"attribute": "Defense", "value": 5},
			{"attribute": "Constitution", "value": 7},
			{"attribute": "Dexterity", "value": 5},
			{"attribute": "Health", "value": -1},
			{"attribute": "Velocity", "value": 10},
			{"attribute": "ManaMax", "value": -10},
			{"attribute": "DamageReductionPhysical", "value": 3}
		],
		"abilities": []
	}, {
		"name": "Leather Boots",
		"type": "Feet",
		"rarity": 2,
		"sellPrice": [37],
		"dimensInvent": {
			"width": 2, "height": 2
		},
		"attributeMods": [
			{"attribute": "Defense", "value": 6},
			{"attribute": "Constitution", "value": 8},
			{"attribute": "Health", "value": -2},
			{"attribute": "Dexterity", "value": 3},
			{"attribute": "Velocity", "value": 7},
			{"attribute": "ManaMax", "value": -5},
			{"attribute": "DamageReductionPhysical", "value": 3}
		],
		"abilities": []
	}, {
		"name": "Leather Helmet",
		"type": "Head",
		"rarity": 2,
		"sellPrice": [28],
		"dimensInvent": {
			"width": 2, "height": 2
		},
		"attributeMods": [
			{"attribute": "LifeMax", "value": 11},
			{"attribute": "Defense", "value": 4},
			{"attribute": "Constitution", "value": 5},
			{"attribute": "Health", "value": -2},
			{"attribute": "DamageReductionPhysical", "value": 3},
			{"attribute": "DamageReductionMagical", "value": 1},
			{"attribute": "CriticalMultiplierReduction", "value": 7}
		],
		"abilities": []
	}, {
		"name": "Leather Gloves",
		"type": "Hands",
		"rarity": 2,
		"sellPrice": [22],
		"dimensInvent": {
			"width": 2, "height": 2
		},
		"attributeMods": [
			{"attribute": "Defense", "value": 3},
			{"attribute": "Constitution", "value": 2},
			{"attribute": "Health", "value": -2},
			{"attribute": "Precision", "value": 3},
			{"attribute": "Dexterity", "value": 4},
			{"attribute": "DamageReductionPhysical", "value": 2},
			{"attribute": "ProbabilityHitPhysical", "value": 3},
			{"attribute": "ProbabilityHitMagical", "value": 3}
		],
		"abilities": []
	}, {
		"name": "Leather Sleeve",
		"type": "Arms",
		"rarity": 2,
		"sellPrice": [13],
		"dimensInvent": {
			"width": 1, "height": 2
		},
		"attributeMods": [
			{"attribute": "Strength", "value": 3},
			{"attribute": "Defense", "value": 4},
			{"attribute": "Constitution", "value": 6},
			{"attribute": "Health", "value": -2},
			{"attribute": "Precision", "value": 4},
			{"attribute": "Dexterity", "value": -5},
			{"attribute": "DamageReductionPhysical", "value": 2},
			{"attribute": "CriticalMultiplierReduction", "value": 5},
			{"attribute": "DamageReductionMagical", "value": 2}
		],
		"abilities": []
	}, {
		"name": "Leather Belt",
		"type": "Belt",
		"rarity": 1,
		"sellPrice": [24],
		"dimensInvent": {
			"width": 2, "height": 1
		},
		"attributeMods": [
			{"attribute": "Strength", "value": 4},
			{"attribute": "Constitution", "value": 3},
			{"attribute": "Dexterity", "value": 2},
			{"attribute": "Defense", "value": 2}
		],
		"abilities": []
	}, {
		"name": "Belt with iron plates",
		"type": "Belt",
		"rarity": 2,
		"sellPrice": [39],
		"dimensInvent": {
			"width": 2, "height": 1
		},
		"attributeMods": [
			{"attribute": "Strength", "value": 3},
			{"attribute": "Constitution", "value": 5},
			{"attribute": "Defense", "value": 5},
			{"attribute": "Dexterity", "value": -3},
			{"attribute": "DamageReductionPhysical", "value": 2}
		],
		"abilities": []
	}, {
		"name": "String belt",
		"type": "Belt",
		"rarity": 1,
		"sellPrice": [16],
		"dimensInvent": {
			"width": 2, "height": 1
		},
		"attributeMods": [
			{"attribute": "Strength", "value": 1},
			{"attribute": "Constitution", "value": 2},
			{"attribute": "Defense", "value": 3},
			{"attribute": "Dexterity", "value": 2},
			{"attribute": "DamageReductionMagical", "value": 1},
		],
		"abilities": []
	}, {
		"name": "Ruby Ring",
		"type": "Ring",
		"rarity": 1,
		"sellPrice": [33],
		"dimensInvent": {
			"width": 1, "height": 1
		},
		"attributeMods": [
			{"attribute": "Strength", "value": 4}
		],
		"abilities": []
	}, {
		"name": "Oxided Iron Ring",
		"type": "Ring",
		"rarity": 1,
		"sellPrice": [33],
		"dimensInvent": {
			"width": 1, "height": 1
		},
		"attributeMods": [
			{"attribute": "LifeMax", "value": 30}
		],
		"abilities": []
	}, {
		"name": "Lapis Lazuli Ring",
		"type": "Ring",
		"rarity": 1,
		"sellPrice": [33],
		"dimensInvent": {
			"width": 1, "height": 1
		},
		"attributeMods": [
			{"attribute": "ManaMax", "value": 25}
		],
		"abilities": []
	}, {
		"name": "Amber Ring",
		"type": "Ring",
		"rarity": 1,
		"sellPrice": [33],
		"dimensInvent": {
			"width": 1, "height": 1
		},
		"attributeMods": [
			{"attribute": "Precision", "value": 4}
		],
		"abilities": []
	}, {
		"name": "Emerald Ring",
		"type": "Ring",
		"rarity": 1,
		"sellPrice": [33],
		"dimensInvent": {
			"width": 1, "height": 1
		},
		"attributeMods": [
			{"attribute": "Dexterity", "value": 4}
		],
		"abilities": []
	}, {
		"name": "Ring of fearful animal",
		"type": "Ring",
		"description": "Fear have a strong power: in long run, can endure sense at the cost of lucidity.",
		"rarity": 1,
		"sellPrice": [27],
		"dimensInvent": {
			"width": 1, "height": 1
		},
		"attributeMods": [
			{"attribute": "Dexterity", "value": 7},
			{"attribute": "Intelligence", "value": -2},
			{"attribute": "Wisdom", "value": -1},
			{"attribute": "CriticalProbabilityAvoid", "value": 4}
		],
		"abilities": []
	}, {
		"name": "Sapphire Ring",
		"type": "Ring",
		"rarity": 1,
		"sellPrice": [33],
		"dimensInvent": {
			"width": 1, "height": 1
		},
		"attributeMods": [
			{"attribute": "Intelligence", "value": 4}
		],
		"abilities": []
	}, {
		"name": "Tiger Eye Ring",
		"type": "Ring",
		"rarity": 1,
		"sellPrice": [33],
		"dimensInvent": {
			"width": 1, "height": 1
		},
		"attributeMods": [
			{"attribute": "RegenLife", "value": 2}
		],
		"abilities": []
	}, {
		"name": "Opal Ring",
		"type": "Ring",
		"rarity": 1,
		"sellPrice": [33],
		"dimensInvent": {
			"width": 1, "height": 1
		},
		"attributeMods": [
			{"attribute": "RegenMana", "value": 2}
		],
		"abilities": []
	}, {
		"name": "Aquamarine Ring",
		"type": "Ring",
		"rarity": 1,
		"sellPrice": [33],
		"dimensInvent": {
			"width": 1, "height": 1
		},
		"attributeMods": [
			{"attribute": "Wisdom", "value": 4}
		],
		"abilities": []
	}, {
		"name": "Quartz Ring",
		"type": "Ring",
		"rarity": 1,
		"sellPrice": [42],
		"dimensInvent": {
			"width": 1, "height": 1
		},
		"attributeMods": [
			{"attribute": "RegenLife", "value": 1},
			{"attribute": "RegenMana", "value": 1}
		],
		"abilities": []
	}, {
		"name": "Body Quartz Ring",
		"type": "Ring",
		"rarity": 1,
		"sellPrice": [40],
		"dimensInvent": {
			"width": 1, "height": 1
		},
		"attributeMods": [
			{"attribute": "RegenLife", "value": 3},
			{"attribute": "RegenMana", "value": -1}
		],
		"abilities": []
	}, {
		"name": "Mind Quartz Ring",
		"type": "Ring",
		"rarity": 1,
		"sellPrice": [40],
		"dimensInvent": {
			"width": 1, "height": 1
		},
		"attributeMods": [
			{"attribute": "RegenLife", "value": -1},
			{"attribute": "RegenMana", "value": 3}
		],
		"abilities": []
	}, {
		"name": "Rhyolite Ring",
		"type": "Ring",
		"rarity": 2,
		"sellPrice": [47],
		"dimensInvent": {
			"width": 1, "height": 1
		},
		"attributeMods": [
			{"attribute": "RegenLife", "value": 1},
			{"attribute": "LifeMax", "value": 20}
		],
		"abilities": []
	}, {
		"name": "Spectrolite Ring",
		"type": "Ring",
		"rarity": 1,
		"sellPrice": [40],
		"dimensInvent": {
			"width": 1, "height": 1
		},
		"attributeMods": [
			{"attribute": "ManaMax", "value": 20},
			{"attribute": "RegenMana", "value": 1}
		],
		"abilities": []
	}, {
		"name": "Serpentine Ring",
		"type": "Ring",
		"rarity": 2,
		"sellPrice": [38],
		"dimensInvent": {
			"width": 1, "height": 1
		},
		"attributeMods": [
			{"attribute": "Defense", "value": 2},
			{"attribute": "Dexterity", "value": 2},
			{"attribute": "Precision", "value": 2}
		],
		"abilities": []
	}, {
		"name": "Spinel Ring",
		"type": "Ring",
		"rarity": 1,
		"sellPrice": [33],
		"dimensInvent": {
			"width": 1, "height": 1
		},
		"attributeMods": [
			{"attribute": "Health", "value": 4}
		],
		"abilities": []
	}, {
		"name": "Diamond Ring",
		"type": "Ring",
		"rarity": 3,
		"sellPrice": [65],
		"dimensInvent": {
			"width": 1, "height": 1
		},
		"attributeMods": [
			{"attribute": "Luck", "value": 5}
		],
		"abilities": []
	}, {
		"name": "Andesine Ring",
		"type": "Ring",
		"rarity": 1,
		"sellPrice": [33],
		"dimensInvent": {
			"width": 1, "height": 1
		},
		"attributeMods": [
			{"attribute": "Constitution", "value": 4}
		],
		"abilities": []
	}, {
		"name": "Amazonite Ring",
		"type": "Ring",
		"rarity": 1,
		"sellPrice": [33],
		"dimensInvent": {
			"width": 1, "height": 1
		},
		"attributeMods": [
			{"attribute": "Faith", "value": 4}
		],
		"abilities": []
	}, {
		"name": "Calcite Ring",
		"type": "Ring",
		"rarity": 1,
		"sellPrice": [33],
		"dimensInvent": {
			"width": 1, "height": 1
		},
		"attributeMods": [
			{"attribute": "Velocity", "value": 10}
		],
		"abilities": []
	}, {
		"name": "Rhodonite Ring",
		"type": "Ring",
		"rarity": 1,
		"sellPrice": [33],
		"dimensInvent": {
			"width": 1, "height": 1
		},
		"attributeMods": [
			{"attribute": "DamageBonusMagical", "value": 2}
		],
		"abilities": []
	}, {
		"name": "Malachite Ring",
		"type": "Ring",
		"rarity": 1,
		"sellPrice": [33],
		"dimensInvent": {
			"width": 1, "height": 1
		},
		"attributeMods": [
			{"attribute": "DamageReductionMagical", "value": 2}
		],
		"abilities": []
	}, {
		"name": "Moldavite Ring",
		"type": "Ring",
		"rarity": 1,
		"sellPrice": [33],
		"dimensInvent": {
			"width": 1, "height": 1
		},
		"attributeMods": [
			{"attribute": "DamageBonusPhysical", "value": 2}
		],
		"abilities": []
	}, {
		"name": "Morganite Ring",
		"type": "Ring",
		"rarity": 1,
		"sellPrice": [33],
		"dimensInvent": {
			"width": 1, "height": 1
		},
		"attributeMods": [
			{"attribute": "DamageReductionPhysical", "value": 2}
		],
		"abilities": []
	}, {
		"name": "Sphene Ring",
		"type": "Ring",
		"rarity": 1,
		"sellPrice": [33],
		"dimensInvent": {
			"width": 1, "height": 1
		},
		"attributeMods": [
			{"attribute": "CriticalProbability", "value": 10}
		],
		"abilities": []
	}, {
		"name": "Sugilite Ring",
		"type": "Ring",
		"rarity": 1,
		"sellPrice": [33],
		"dimensInvent": {
			"width": 1, "height": 1
		},
		"attributeMods": [
			{"attribute": "CriticalMultiplier", "value": 5}
		],
		"abilities": []
	}, {
		"name": "Blue Topaz Ring",
		"type": "Ring",
		"rarity": 2,
		"sellPrice": [48],
		"dimensInvent": {
			"width": 1, "height": 1
		},
		"attributeMods": [
			{"attribute": "DamageBonusMagical", "value": 2},
			{"attribute": "DamageReductionMagical", "value": 1}
		],
		"abilities": []
	}, {
		"name": "Light-Blue Topaz Ring",
		"type": "Ring",
		"rarity": 2,
		"sellPrice": [48],
		"dimensInvent": {
			"width": 1, "height": 1
		},
		"attributeMods": [
			{"attribute": "DamageBonusMagical", "value": 1},
			{"attribute": "DamageReductionMagical", "value": 2}
		],
		"abilities": []
	}, {
		"name": "Triphane Ring",
		"type": "Ring",
		"rarity": 2,
		"sellPrice": [48],
		"dimensInvent": {
			"width": 1, "height": 1
		},
		"attributeMods": [
			{"attribute": "Dexterity", "value": 3},
			{"attribute": "Precision", "value": 2}
		],
		"abilities": []
	}, {
		"name": "Verdite Ring",
		"type": "Ring",
		"rarity": 2,
		"sellPrice": [48],
		"dimensInvent": {
			"width": 1, "height": 1
		},
		"attributeMods": [
			{"attribute": "Dexterity", "value": 2},
			{"attribute": "Precision", "value": 3}
		],
		"abilities": []
	}, {
		"name": "Yellow Zoisite Ring",
		"type": "Ring",
		"rarity": 2,
		"sellPrice": [55],
		"dimensInvent": {
			"width": 1, "height": 1
		},
		"attributeMods": [
			{"attribute": "DamageBonusPhysical", "value": 2},
			{"attribute": "DamageReductionPhysical", "value": 1}
		],
		"abilities": []
	}, {
		"name": "Green Zoisite Ring",
		"type": "Ring",
		"rarity": 2,
		"sellPrice": [55],
		"dimensInvent": {
			"width": 1, "height": 1
		},
		"attributeMods": [
			{"attribute": "DamageBonusPhysical", "value": 1},
			{"attribute": "DamageReductionPhysical", "value": 2}
		],
		"abilities": []
	}, {
		"name": "Sunstone Ring",
		"type": "Ring",
		"rarity": 3,
		"sellPrice": [65],
		"dimensInvent": {
			"width": 2, "height": 1
		},
		"attributeMods": [
			{"attribute": "LifeMax", "value": 25},
			{"attribute": "Strength", "value": 2},
			{"attribute": "Constitution", "value": 2},
			{"attribute": "Health", "value": 2},
			{"attribute": "RegenLife", "value": 2}

		],
		"abilities": []
	}, {
		"name": "Moonstone Ring",
		"type": "Ring",
		"rarity": 3,
		"sellPrice": [65],
		"dimensInvent": {
			"width": 2, "height": 1
		},
		"attributeMods": [
			{"attribute": "ManaMax", "value": 15},
			{"attribute": "Intelligence", "value": 2},
			{"attribute": "Wisdom", "value": 2},
			{"attribute": "Faith", "value": 2},
			{"attribute": "RegenMana", "value": 2},
			{"attribute": "Luck", "value": 1}
		],
		"abilities": []
	}, {
		"name": "Pyrite Ring",
		"type": "Ring",
		"rarity": 2,
		"sellPrice": [40],
		"dimensInvent": {
			"width": 1, "height": 1
		},
		"attributeMods": [
			{"attribute": "DamageBonusPhysical", "value": 2},
			{"attribute": "DamageBonusMagical", "value": 2},
			{"attribute": "RegenLife", "value": -1},
			{"attribute": "RegenMana", "value": -1}
		],
		"abilities": []
	}, {
		"name": "Prehnite Ring",
		"type": "Ring",
		"rarity": 2,
		"sellPrice": [55],
		"dimensInvent": {
			"width": 1, "height": 1
		},
		"attributeMods": [
			{"attribute": "DamageReductionPhysical", "value": 2},
			{"attribute": "DamageReductionMagical", "value": 2},
			{"attribute": "Luck", "value": -1}
		],
		"abilities": []
	}, {
		"name": "Plated Armor of Stonefying Skin",
		"type": "Chest",
		"rarity": 3,
		"sellPrice": [155],
		"dimensInvent": {
			"width": 2, "height": 3
		},
		"attributeMods": [
			{"attribute": "Constitution", "value": 2},
			{"attribute": "Health", "value": -5},
			{"attribute": "Defense", "value": 7},
			{"attribute": "Dexterity", "value": -6},
			{"attribute": "DamageReductionPhysical", "value": 3},
			{"attribute": "DamageReductionMagical", "value": 3}
		],
		"abilities": ["Stonefying Skin"]
	}, {
		"name": "Belt with Limph-made Walled",
		"type": "Belt",
		"rarity": 3,
		"sellPrice": [203],
		"dimensInvent": {
			"width": 2, "height": 1
		},
		"attributeMods": [
			{"attribute": "RegenLife", "value": 2},
			{"attribute": "Luck", "value": -4}
		],
		"abilities": ["Healthy wallet in healthy body"]
	}, {
		"name": "Bracelet of a child",
		"type": "Bracelet",
		"rarity": 1,
		"sellPrice": [15],
		"dimensInvent": {
			"width": 1, "height": 1
		},
		"attributeMods": [
			{"attribute": "Health", "value": 1},
			{"attribute": "Faith", "value": 2},
			{"attribute": "Luck", "value": 2}
		],
		"abilities": []
	}, {
		"name": "Bracelet of river stones",
		"type": "Bracelet",
		"rarity": 1,
		"sellPrice": [17],
		"dimensInvent": {
			"width": 1, "height": 1
		},
		"attributeMods": [
			{"attribute": "Constitution", "value": 2},
			{"attribute": "Wisdom", "value": 1},
			{"attribute": "Faith", "value": 2},
			{"attribute": "Dexterity", "value": -1}
		],
		"abilities": []
	}, {
		"name": "Bracelet of animal bones",
		"type": "Bracelet",
		"rarity": 2,
		"sellPrice": [22],
		"dimensInvent": {
			"width": 1, "height": 1
		},
		"attributeMods": [
			{"attribute": "Constitution", "value": 2},
			{"attribute": "Dexterity", "value": 2},
			{"attribute": "Wisdom", "value": 1},
			{"attribute": "Faith", "value": 2}
		],
		"abilities": []
	}, {
		"name": "Bracelet of wolves teeth",
		"type": "Bracelet",
		"rarity": 3,
		"sellPrice": [35],
		"dimensInvent": {
			"width": 1, "height": 1
		},
		"attributeMods": [
			{"attribute": "Strength", "value": 5},
			{"attribute": "Precision", "value": 6},
			{"attribute": "Dexterity", "value": 4},
			{"attribute": "Faith", "value": -2}
		],
		"abilities": []
	}, {
		"name": "Bracelet of precious stones",
		"type": "Bracelet",
		"rarity": 3,
		"sellPrice": [42],
		"dimensInvent": {
			"width": 1, "height": 1
		},
		"attributeMods": [
			{"attribute": "Intelligence", "value": 3},
			{"attribute": "Wisdom", "value": 3},
			{"attribute": "Faith", "value": 3},
			{"attribute": "Luck", "value": 2}
		],
		"abilities": []
	}, {
		"name": "Bracelet with metal bands",
		"type": "Bracelet",
		"rarity": 3,
		"sellPrice": [42],
		"dimensInvent": {
			"width": 1, "height": 1
		},
		"attributeMods": [
			{"attribute": "Strength", "value": 3},
			{"attribute": "Constitution", "value": 3},
			{"attribute": "Health", "value": 3},
			{"attribute": "Luck", "value": 2}
		],
		"abilities": []
	}, {
		"name": "Bracelet of runed woods",
		"type": "Bracelet",
		"rarity": 3,
		"sellPrice": [42],
		"dimensInvent": {
			"width": 1, "height": 1
		},
		"attributeMods": [
			{"attribute": "Defense", "value": 3},
			{"attribute": "Dexterity", "value": 3},
			{"attribute": "Precision", "value": 3},
			{"attribute": "Luck", "value": 2}
		],
		"abilities": []
	}, {
		"name": "Bracelet of flowers and leaves",
		"type": "Bracelet",
		"rarity": 2,
		"sellPrice": [26],
		"dimensInvent": {
			"width": 1, "height": 1
		},
		"attributeMods": [
			{"attribute": "LifeMax", "value": 15},
			{"attribute": "ManaMax", "value": 10},
			{"attribute": "Health", "value": 2},
			{"attribute": "Faith", "value": 2}
		],
		"abilities": []
	}, {
		"name": "Bracelet gold plated",
		"type": "Bracelet",
		"rarity": 4,
		"sellPrice": [170],
		"dimensInvent": {
			"width": 1, "height": 1
		},
		"attributeMods": [
			{"attribute": "DamageBonusMagical", "value": 3},
			{"attribute": "DamageReductionMagical", "value": 4},
			{"attribute": "Luck", "value": -5},
			{"attribute": "Faith", "value": 4}
		],
		"abilities": []
	}, {
		"name": "Bracelet silver plated",
		"type": "Bracelet",
		"rarity": 3,
		"sellPrice": [80],
		"dimensInvent": {
			"width": 1, "height": 1
		},
		"attributeMods": [
			{"attribute": "DamageBonusMagical", "value": 1},
			{"attribute": "DamageReductionMagical", "value": 2},
			{"attribute": "Luck", "value": -2},
			{"attribute": "Faith", "value": 2}
		],
		"abilities": []
	}, {
		"name": "Belt of the Warrior",
		"type": "Belt",
		"rarity": 3,
		"sellPrice": [40],
		"dimensInvent": {
			"width": 2, "height": 1
		},
		"attributeMods": [
			{"attribute": "Strength", "value": 7},
			{"attribute": "Constitution", "value": 5},
			{"attribute": "Health", "value": 3},
			{"attribute": "DamageReductionPhysical", "value": 1},
			{"attribute": "DamageBonusPhysical", "value": 1}
		],
		"abilities": []
	}, {
		"name": "Belt of the Druid",
		"type": "Belt",
		"rarity": 3,
		"sellPrice": [40],
		"dimensInvent": {
			"width": 2, "height": 1
		},
		"attributeMods": [
			{"attribute": "Defense", "value": 3},
			{"attribute": "Dexterity", "value": 6},
			{"attribute": "Precision", "value": 6},
			{"attribute": "CriticalMultiplier", "value": 4},
			{"attribute": "CriticalProbability", "value": 20}
		],
		"abilities": []
	}, {
		"name": "Belt of the Bishop",
		"type": "Belt",
		"rarity": 3,
		"sellPrice": [40],
		"dimensInvent": {
			"width": 2, "height": 1
		},
		"attributeMods": [
			{"attribute": "Intelligence", "value": 4},
			{"attribute": "Wisdom", "value": 5},
			{"attribute": "Faith", "value": 6},
			{"attribute": "DamageReductionMagical", "value": 1},
			{"attribute": "DamageBonusMagical", "value": 1}
		],
		"abilities": []
	}, {
		"name": "Earrings of little hunger",
		"type": "Earrings",
		"rarity": 2,
		"sellPrice": [15],
		"dimensInvent": {
			"width": 1, "height": 1
		},
		"attributeMods": [
			{"attribute": "Health", "value": -5},
			{"attribute": "RegenLife", "value": 2}
		],
		"abilities": []
	}, {
		"name": "Earrings of rusted plate",
		"type": "Earrings",
		"rarity": 1,
		"sellPrice": [7],
		"dimensInvent": {
			"width": 1, "height": 1
		},
		"attributeMods": [
			{"attribute": "Health", "value": 5},
			{"attribute": "RegenLife", "value": -2}
		],
		"abilities": []
	}, {
		"name": "Ring of rusted plate",
		"type": "Ring",
		"rarity": 1,
		"sellPrice": [7],
		"dimensInvent": {
			"width": 1, "height": 1
		},
		"attributeMods": [
			{"attribute": "Health", "value": 5},
			{"attribute": "RegenLife", "value": -2}
		],
		"abilities": []
	}, {
		"name": "Gloves of the mad hunter",
		"description": "Gloves belonged to a bloody madman, who always became crazy and frenzy if he cannot satisfy his cruelty upon missing the target.",
		"type": "Hands",
		"rarity": 3,
		"sellPrice": [5],
		"dimensInvent": {
			"width": 2, "height": 2
		},
		"attributeMods": [
			{"attribute": "Defense", "value": 3},
			{"attribute": "Strength", "value": 4},
			{"attribute": "Precision", "value": 2},
			{"attribute": "Dexterity", "value": 2}
		],
		"abilities": ["Frenzy for a miss"]
	}, {
		"name": "Necklace of devoted vampire",
		"type": "Necklace",
		"rarity": 3,
		"sellPrice": [76],
		"dimensInvent": {
			"width": 1, "height": 2
		},
		"attributeMods": [
			{"attribute": "Faith", "value": 4},
			{"attribute": "LifeLeechPercentage", "value": 10},
			{"attribute": "Precision", "value": 7},
			{"attribute": "Luck", "value": -3},
			{"attribute": "Constitution", "value": -12},
			{"attribute": "Strength", "value": -4}
		],
		"abilities": ["Bloodlust"]
	}, {
		"name": "Bead of the dance",
		"type": "Necklace",
		"rarity": 1,
		"sellPrice": [17],
		"dimensInvent": {
			"width": 1, "height": 1
		},
		"attributeMods": [
			{"attribute": "LifeMax", "value": 30},
			{"attribute": "Dexterity", "value": 4}
		],
		"abilities": []
	}, {
		"name": "Pendant with Eye of the tiger",
		"type": "Necklace",
		"rarity": 1,
		"sellPrice": [17],
		"dimensInvent": {
			"width": 1, "height": 1
		},
		"attributeMods": [
			{"attribute": "ManaMax", "value": 30},
			{"attribute": "Precision", "value": 4}
		],
		"abilities": []
	}, {
		"name": "Choker of inebriance",
		"type": "Necklace",
		"rarity": 2,
		"sellPrice": [14],
		"dimensInvent": {
			"width": 1, "height": 2
		},
		"attributeMods": [
			{"attribute": "RegenLife", "value": 2},
			{"attribute": "RegenMana", "value": 2},
			{"attribute": "Intelligence", "value": -3},
			{"attribute": "Strength", "value": -3}
		],
		"abilities": []
	}, {
		"name": "Necklace of the tribu",
		"type": "Necklace",
		"description": "Devoted to Nature, this simple ornament represent their bound: armony without pain.",
		"rarity": 2,
		"sellPrice": [18],
		"dimensInvent": {
			"width": 1, "height": 2
		},
		"attributeMods": [
			{"attribute": "Health", "value": 4},
			{"attribute": "Faith", "value": 4},
			{"attribute": "DamageBonusPhysical", "value": -1},
			{"attribute": "DamageBonusMagical", "value": -1}
		],
		"abilities": []
	}, {
		"name": "Warm scarf",
		"type": "Necklace",
		"rarity": 1,
		"sellPrice": [8],
		"dimensInvent": {
			"width": 1, "height": 1
		},
		"attributeMods": [
			{"attribute": "Health", "value": 4},
			{"attribute": "RegenLife", "value": 1},
			{"attribute": "DamageReductionMagical", "value": -2}
		],
		"abilities": []
	}, {
		"name": "Amulet of spiritual guardian",
		"type": "Necklace",
		"rarity": 3,
		"sellPrice": [47],
		"dimensInvent": {
			"width": 1, "height": 1
		},
		"attributeMods": [
			{"attribute": "ManaMax", "value": -25},
			{"attribute": "RegenMana", "value": -7},
			{"attribute": "DamageReductionMagical", "value": 8},
			{"attribute": "DamageReductionPhysical", "value": 3},
			{"attribute": "CriticalMultiplierReduction", "value": 15}
		],
		"abilities": []
	}, {
		"name": "Earrings of hard touch",
		"type": "Earrings",
		"rarity": 2,
		"sellPrice": [22],
		"dimensInvent": {
			"width": 1, "height": 1
		},
		"attributeMods": [
			{"attribute": "DamageBonusPhysical", "value": -10},
			{"attribute": "DamageBonusMagical", "value": -10},
			{"attribute": "CriticalMultiplier", "value": 30}
		],
		"abilities": []
	}, {
		"name": "Gloves of soft touch",
		"type": "Hands",
		"rarity": 1,
		"sellPrice": [12],
		"dimensInvent": {
			"width": 1, "height": 1
		},
		"attributeMods": [
			{"attribute": "Health", "value": 5},
			{"attribute": "Faith", "value": 3},
			{"attribute": "DamageBonusPhysical", "value": -7},
			{"attribute": "DamageBonusMagical", "value": -7},
			{"attribute": "CriticalMultiplier", "value": -20},
			{"attribute": "DamageReductionPhysical", "value": 7},
			{"attribute": "DamageReductionMagical", "value": 7},
			{"attribute": "CriticalMultiplierReduction", "value": 20}
		],
		"abilities": []
	}, {
		"name": "Crystal armguard",
		"type": "Arms",
		"rarity": 4,
		"sellPrice": [230],
		"dimensInvent": {
			"width": 1, "height": 2
		},
		"attributeMods": [
			{"attribute": "ShieldMax", "value": 50},
			{"attribute": "RegenShield", "value": 5},
			{"attribute": "DamageBonusMagical", "value": 12},
			{"attribute": "CriticalMultiplier", "value": 15},
			{"attribute": "CriticalMultiplierReduction", "value": -20}
		],
		"abilities": []
	}, {
		"name": "Runed armguard",
		"type": "Arms",
		"rarity": 3,
		"sellPrice": [80],
		"dimensInvent": {
			"width": 1, "height": 2
		},
		"attributeMods": [
			{"attribute": "LifeMax", "value": -40},
			{"attribute": "ManaMax", "value": -50},
			{"attribute": "RegenMana", "value": -7},
			{"attribute": "Strength", "value": 4},
			{"attribute": "Intelligence", "value": 5},
			{"attribute": "Wisdom", "value": 8},
			{"attribute": "Dexterity", "value": 5},
			{"attribute": "Precision", "value": 7},
			{"attribute": "DamageBonusPhysical", "value": 4},
			{"attribute": "DamageBonusMagical", "value": 4},
			{"attribute": "CriticalMultiplier", "value": 5}
		],
		"abilities": []
	}, {
		"name": "Gems Necklace of Meditation",
		"type": "Necklace",
		"rarity": 2,
		"sellPrice": [44],
		"dimensInvent": {
			"width": 1, "height": 2
		},
		"attributeMods": [
			{"attribute": "RegenLife", "value": 2},
			{"attribute": "RegenMana", "value": 2},
			{"attribute": "Health", "value": 4},
			{"attribute": "Constitution", "value": 3},
			{"attribute": "Wisdom", "value": 4},
			{"attribute": "Faith", "value": 8},
			{"attribute": "Strength", "value": -5}
		],
		"abilities": ["AMeditationMoreRegen 2"]
	}
]